<ModOps>
        <!-- # Adding residence to AP - All Buildings that need a street connection -->
    <ModOp Type="AddNextSibling" GUID="1010343">
        <Asset>
            <Template>ResidenceBuilding</Template>
            <Values>
                <Standard>
                    <GUID>1555600001</GUID>
                    <Name>AI_residence_tier01</Name>
                    <IconFilename>data/ui/2kimages/main/3dicons/icon_resident.png</IconFilename>
                    <InfoDescription>163059</InfoDescription>
                    <!--residence 01 infocorner-->
                </Standard>
                <Blocking/>
                <Building>
                    <BuildingType>Residence</BuildingType>
                    <SkipUnlockMessage>1</SkipUnlockMessage>
                    <BuildModeRandomRotation>90</BuildModeRandomRotation>
                    <AssociatedRegions>Moderate</AssociatedRegions>
                </Building>
                <Cost>
                    <Costs>
                        <Item>
                            <VectorElement>
                                <InheritedIndex>0</InheritedIndex>
                                <InheritanceMapV2>
                                    <Entry>
                                        <TemplateName>ResidenceBuilding</TemplateName>
                                        <Index>0</Index>
                                    </Entry>
                                </InheritanceMapV2>
                            </VectorElement>
                        </Item>
                        <Item>
                            <Ingredient>1010196</Ingredient>
                            <!--timber-->
                            <Amount>2</Amount>
                        </Item>
                        <Item>
                            <VectorElement>
                                <InheritedIndex>2</InheritedIndex>
                                <InheritanceMapV2>
                                    <Entry>
                                        <TemplateName>ResidenceBuilding</TemplateName>
                                        <Index>2</Index>
                                    </Entry>
                                </InheritanceMapV2>
                            </VectorElement>
                        </Item>
                        <Item>
                            <VectorElement>
                                <InheritedIndex>3</InheritedIndex>
                                <InheritanceMapV2>
                                    <Entry>
                                        <TemplateName>ResidenceBuilding</TemplateName>
                                        <Index>3</Index>
                                    </Entry>
                                </InheritanceMapV2>
                            </VectorElement>
                        </Item>
                        <Item>
                            <VectorElement>
                                <InheritedIndex>4</InheritedIndex>
                                <InheritanceMapV2>
                                    <Entry>
                                        <TemplateName>ResidenceBuilding</TemplateName>
                                        <Index>4</Index>
                                    </Entry>
                                </InheritanceMapV2>
                            </VectorElement>
                        </Item>
                        <Item>
                            <VectorElement>
                                <InheritedIndex>5</InheritedIndex>
                                <InheritanceMapV2>
                                    <Entry>
                                        <TemplateName>ResidenceBuilding</TemplateName>
                                        <Index>5</Index>
                                    </Entry>
                                </InheritanceMapV2>
                            </VectorElement>
                        </Item>
                    </Costs>
                </Cost>
                <Mesh/>
                <Object>
                    <Variations>
                        <Item>
                            <Filename>data/cdlc06/graphics/buildings/residence/residence_tier01_01_estate01/residence_tier01_01_estate01.cfg</Filename>
                        </Item>
                        <Item>
                            <Filename>data/cdlc06/graphics/buildings/residence/residence_tier01_01_estate02/residence_tier01_01_estate02.cfg</Filename>
                        </Item>
                        <Item>
                            <Filename>data/cdlc06/graphics/buildings/residence/residence_tier01_01_estate03/residence_tier01_01_estate03.cfg</Filename>
                        </Item>
                        <Item>
                            <Filename>data/cdlc06/graphics/buildings/residence/residence_tier01_01_estate04/residence_tier01_01_estate04.cfg</Filename>
                        </Item>
                    </Variations>
                    <Skins>
                        <DefaultSkinName>1010343</DefaultSkinName>
                        <DefaultSkinDescription>23853</DefaultSkinDescription>
                        <!--ChangeBuildingSkin_toDefaultSkinDesc-->
                        <DefaultSkinCategoryName>7312</DefaultSkinCategoryName>
                        <!--Classic-->
                        <OverrideDefaultIcon>data/ui/2kimages/main/3dicons/ornaments/cosmetic_dlc06/icon_tier01_default.png</OverrideDefaultIcon>
                        <SkinList>
                            <Item>
                                <SkinAssetGuid>694</SkinAssetGuid>
                                <!--Skin Residence T01_S01-->
                            </Item>
                            <Item>
                                <SkinAssetGuid>702</SkinAssetGuid>
                                <!--Skin Residence T01_S03-->
                            </Item>
                            <Item>
                                <SkinAssetGuid>716</SkinAssetGuid>
                                <!--Skin Residence T01_S04-->
                            </Item>
                        </SkinList>
                    </Skins>
                </Object>
                <Selection>
                    <OnSelection>
                        <IsBaseAutoCreateAsset>1</IsBaseAutoCreateAsset>
                        <Values>
                            <ActionList/>
                        </Values>
                    </OnSelection>
                    <ParticipantMessageArcheType>Resident_tier01</ParticipantMessageArcheType>
                </Selection>
                <Text>
                    <LocaText>
                        <English>
                            <Text>Farmer Residence</Text>
                            <Status>Exported</Status>
                        </English>
                    </LocaText>
                    <LineID>5227</LineID>
                </Text>
                <Constructable/>
                <Locked>
                    <DefaultLockedState>0</DefaultLockedState>
                </Locked>
                <Upgradable>
                    <NextGUID>1555600002</NextGUID>
                    <!--AI_residence_tier02-->
                    <UpgradeCost>
                        <Item>
                            <VectorElement>
                                <InheritedIndex>0</InheritedIndex>
                                <InheritanceMapV2>
                                    <Entry>
                                        <TemplateName>ResidenceBuilding</TemplateName>
                                        <Index>0</Index>
                                    </Entry>
                                </InheritanceMapV2>
                            </VectorElement>
                        </Item>
                        <Item>
                            <Amount>4</Amount>
                            <Ingredient>1010196</Ingredient>
                            <!--timber-->
                        </Item>
                        <Item>
                            <VectorElement>
                                <InheritedIndex>2</InheritedIndex>
                                <InheritanceMapV2>
                                    <Entry>
                                        <TemplateName>ResidenceBuilding</TemplateName>
                                        <Index>2</Index>
                                    </Entry>
                                </InheritanceMapV2>
                            </VectorElement>
                        </Item>
                        <Item>
                            <VectorElement>
                                <InheritedIndex>3</InheritedIndex>
                                <InheritanceMapV2>
                                    <Entry>
                                        <TemplateName>ResidenceBuilding</TemplateName>
                                        <Index>3</Index>
                                    </Entry>
                                </InheritanceMapV2>
                            </VectorElement>
                        </Item>
                        <Item>
                            <VectorElement>
                                <InheritedIndex>4</InheritedIndex>
                                <InheritanceMapV2>
                                    <Entry>
                                        <TemplateName>ResidenceBuilding</TemplateName>
                                        <Index>4</Index>
                                    </Entry>
                                </InheritanceMapV2>
                            </VectorElement>
                        </Item>
                        <Item>
                            <VectorElement>
                                <InheritedIndex>5</InheritedIndex>
                                <InheritanceMapV2>
                                    <Entry>
                                        <TemplateName>ResidenceBuilding</TemplateName>
                                        <Index>5</Index>
                                    </Entry>
                                </InheritanceMapV2>
                            </VectorElement>
                        </Item>
                    </UpgradeCost>
                </Upgradable>
                <SoundEmitter>
                    <ConstructionSounds>
                        <BuildSuccessful>
                            <Item>
                                <VectorElement>
                                    <InheritanceMapV2>
                                        <Entry>
                                            <TemplateName>ResidenceBuilding7</TemplateName>
                                            <Index>0</Index>
                                        </Entry>
                                    </InheritanceMapV2>
                                </VectorElement>
                                <Sound>200776</Sound>
                                <!--wwe_sfx_aui_bld_place_bp-->
                            </Item>
                        </BuildSuccessful>
                        <BuildUpgradeFailed>
                            <Item>
                                <Sound>9818387</Sound>
                                <!--wwe_sfx_aui_deny-->
                            </Item>
                        </BuildUpgradeFailed>
                    </ConstructionSounds>
                    <IncidentSounds>
                        <InfectedFire>
                            <Item>
                                <Sound>214659</Sound>
                                <!--wwe_sfx_bld_inc_burn-->
                            </Item>
                        </InfectedFire>
                        <InfectedIllness>
                            <Item>
                                <Sound>214756</Sound>
                                <!--wwe_sfx_vox_inc_ill_os-->
                            </Item>
                        </InfectedIllness>
                        <InfectedRiot>
                            <Item>
                                <Sound>222229</Sound>
                                <!--wwe_sfx_vox_inc_rio_os-->
                            </Item>
                        </InfectedRiot>
                        <ExplosionOneShots>
                            <Item>
                                <Sound>203849</Sound>
                                <!--wwe_sfx_aui_destroy_small-->
                            </Item>
                        </ExplosionOneShots>
                    </IncidentSounds>
                    <BuildingRepaired>
                        <Item>
                            <Sound>203866</Sound>
                            <!--wwe_sfx_aui_bld_3d_renovate-->
                        </Item>
                    </BuildingRepaired>
                    <MaterialType>Wood</MaterialType>
                </SoundEmitter>
                <Infolayer/>
                <FeedbackController/>
                <Residence7>
                    <ResidenceStorage>
                        <InputStorageMax>1</InputStorageMax>
                    </ResidenceStorage>
                    <PopulationLevel7>15000000</PopulationLevel7>
                    <ResidentMax>10</ResidentMax>
                    <ResidentsRequiredForUpgrade>10</ResidentsRequiredForUpgrade>
                    <IsBaseResidence>1</IsBaseResidence>
                </Residence7>
                <LogisticNode/>
                <AmbientMoodProvider>
                    <DynamicEnvironmentType>ResidenceT1</DynamicEnvironmentType>
                    <HappinessDependentMurmur>
                        <Angry>
                            <Murmur>FarmerUnhappy</Murmur>
                        </Angry>
                        <Unhappy>
                            <Murmur>FarmerContent</Murmur>
                        </Unhappy>
                        <Neutral>
                            <Murmur>FarmerContent</Murmur>
                        </Neutral>
                        <Happy>
                            <Murmur>FarmerHappy</Murmur>
                        </Happy>
                        <Euphoric>
                            <Murmur>FarmerHappy</Murmur>
                        </Euphoric>
                    </HappinessDependentMurmur>
                </AmbientMoodProvider>
                <UpgradeList/>
                <Attackable>
                    <AttackableType>IslandBuilding</AttackableType>
                    <MaximumHitPoints>1500</MaximumHitPoints>
                </Attackable>
                <IncidentInfectable>
                    <Infectable>
                        <Explosion>
                            <Base>0</Base>
                            <Escalated>0</Escalated>
                        </Explosion>
                    </Infectable>
                    <Explosion>
                        <ExplosionCoreDamage>1000</ExplosionCoreDamage>
                    </Explosion>
                    <IncidentInfectionChanceFactors>
                        <Fire>
                            <DensityFactor>0.025</DensityFactor>
                            <DensityDistance>15</DensityDistance>
                        </Fire>
                        <Riot>
                            <ResidenceHappinessFactor>0.4</ResidenceHappinessFactor>
                            <HappinessThreshold>10</HappinessThreshold>
                        </Riot>
                        <Illness>
                            <BaseChance>4</BaseChance>
                            <HitpointFactor>0.1</HitpointFactor>
                            <DensityFactor>0.025</DensityFactor>
                            <DensityDistance>15</DensityDistance>
                            <DilapidatedFactor>10</DilapidatedFactor>
                            <FactoryOvertimeFactor>0.3</FactoryOvertimeFactor>
                            <FactoryUndertimeFactor>0.15</FactoryUndertimeFactor>
                            <ResidenceFullOvertimeChance>20</ResidenceFullOvertimeChance>
                            <ResidenceFullUndertimeChance>-15</ResidenceFullUndertimeChance>
                        </Illness>
                        <Explosion>
                            <ResidenceFullOvertimeChance>20</ResidenceFullOvertimeChance>
                            <ResidenceFullUndertimeChance>-15</ResidenceFullUndertimeChance>
                        </Explosion>
                    </IncidentInfectionChanceFactors>
                </IncidentInfectable>
                <Pausable/>
                <Culture/>
                <StreetActivation/>
                <InfluenceSource/>
                <FloorStackOwner/>
                <Maintenance>
                    <IncomeCategory>Skyscrapers</IncomeCategory>
                </Maintenance>
                <Audio>
                    <ClusterEvent>
                        <IsBaseAutoCreateAsset>1</IsBaseAutoCreateAsset>
                        <Values>
                            <AudioLink/>
                        </Values>
                    </ClusterEvent>
                </Audio>
            </Values>
        </Asset>
        <Asset>
            <Template>ResidenceBuilding</Template>
            <Values>
                <Standard>
                    <GUID>1555600002</GUID>
                    <Name>AI_residence_tier02</Name>
                    <IconFilename>data/ui/2kimages/main/3dicons/icon_resident.png</IconFilename>
                    <InfoDescription>163059</InfoDescription>
                    <!--residence 01 infocorner-->
                </Standard>
                <Blocking/>
                <Building>
                    <BuildingType>Residence</BuildingType>
                    <PickingAsset>1555600001</PickingAsset>
                    <!--residence_tier01-->
                    <AssociatedRegions>Moderate</AssociatedRegions>
                </Building>
                <Cost>
                    <Costs>
                        <Item>
                            <VectorElement>
                                <InheritedIndex>0</InheritedIndex>
                                <InheritanceMapV2>
                                    <Entry>
                                        <TemplateName>ResidenceBuilding</TemplateName>
                                        <Index>0</Index>
                                    </Entry>
                                </InheritanceMapV2>
                            </VectorElement>
                        </Item>
                        <Item>
                            <Ingredient>1010196</Ingredient>
                            <!--timber-->
                            <Amount>6</Amount>
                        </Item>
                        <Item>
                            <VectorElement>
                                <InheritedIndex>2</InheritedIndex>
                                <InheritanceMapV2>
                                    <Entry>
                                        <TemplateName>ResidenceBuilding</TemplateName>
                                        <Index>2</Index>
                                    </Entry>
                                </InheritanceMapV2>
                            </VectorElement>
                        </Item>
                        <Item>
                            <VectorElement>
                                <InheritedIndex>3</InheritedIndex>
                                <InheritanceMapV2>
                                    <Entry>
                                        <TemplateName>ResidenceBuilding</TemplateName>
                                        <Index>3</Index>
                                    </Entry>
                                </InheritanceMapV2>
                            </VectorElement>
                        </Item>
                        <Item>
                            <VectorElement>
                                <InheritedIndex>4</InheritedIndex>
                                <InheritanceMapV2>
                                    <Entry>
                                        <TemplateName>ResidenceBuilding</TemplateName>
                                        <Index>4</Index>
                                    </Entry>
                                </InheritanceMapV2>
                            </VectorElement>
                        </Item>
                        <Item>
                            <VectorElement>
                                <InheritedIndex>5</InheritedIndex>
                                <InheritanceMapV2>
                                    <Entry>
                                        <TemplateName>ResidenceBuilding</TemplateName>
                                        <Index>5</Index>
                                    </Entry>
                                </InheritanceMapV2>
                            </VectorElement>
                        </Item>
                    </Costs>
                </Cost>
                <Mesh/>
                <Object>
                    <Variations>
                        <Item>
                            <Filename>data/graphics/buildings/residence/residence_tier02_estate01/residence_tier02_estate01.cfg</Filename>
                        </Item>
                        <Item>
                            <Filename>data/graphics/buildings/residence/residence_tier02_estate02/residence_tier02_estate02.cfg</Filename>
                        </Item>
                        <Item>
                            <Filename>data/graphics/buildings/residence/residence_tier02_estate03/residence_tier02_estate03.cfg</Filename>
                        </Item>
                        <Item>
                            <Filename>data/graphics/buildings/residence/residence_tier02_estate04/residence_tier02_estate04.cfg</Filename>
                        </Item>
                        <Item>
                            <Filename>data/graphics/buildings/residence/residence_tier02_estate05/residence_tier02_estate05.cfg</Filename>
                        </Item>
                    </Variations>
                    <Skins>
                        <DefaultSkinName>1010344</DefaultSkinName>
                        <DefaultSkinDescription>23853</DefaultSkinDescription>
                        <!--ChangeBuildingSkin_toDefaultSkinDesc-->
                        <DefaultSkinCategoryName>7312</DefaultSkinCategoryName>
                        <!--Classic-->
                        <OverrideDefaultIcon>data/ui/2kimages/main/3dicons/ornaments/cosmetic_dlc06/icon_tier02_default.png</OverrideDefaultIcon>
                        <SkinList>
                            <Item>
                                <SkinAssetGuid>698</SkinAssetGuid>
                                <!--Skin Residence T02_S01-->
                            </Item>
                            <Item>
                                <SkinAssetGuid>709</SkinAssetGuid>
                                <!--Skin Residence T02_S03-->
                            </Item>
                            <Item>
                                <SkinAssetGuid>717</SkinAssetGuid>
                                <!--Skin Residence T02_S04-->
                            </Item>
                            <Item>
                                <SkinAssetGuid>5244</SkinAssetGuid>
                                <!--CDLC09 Residence Tier02-->
                            </Item>
                            <Item>
                                <SkinAssetGuid>30488</SkinAssetGuid>
                                <!--CDLC13 Residence T2 Skin-->
                            </Item>
                        </SkinList>
                    </Skins>
                </Object>
                <Selection>
                    <OnSelection>
                        <IsBaseAutoCreateAsset>1</IsBaseAutoCreateAsset>
                        <Values>
                            <ActionList/>
                        </Values>
                    </OnSelection>
                    <ParticipantMessageArcheType>Resident_tier02</ParticipantMessageArcheType>
                </Selection>
                <Text>
                    <LocaText>
                        <English>
                            <Text>Worker Residence</Text>
                            <Status>Exported</Status>
                        </English>
                    </LocaText>
                    <LineID>5228</LineID>
                </Text>
                <Constructable>
                    <ConstructionMenuIcon>15000001</ConstructionMenuIcon>
                    <!--Moderate Population 2-->
                </Constructable>
                <Locked>
                    <DefaultLockedState>0</DefaultLockedState>
                </Locked>
                <Upgradable>
                    <NextGUID>1555600003</NextGUID>
                    <!--residence_tier03-->
                    <UpgradeCost>
                        <Item>
                            <VectorElement>
                                <InheritedIndex>0</InheritedIndex>
                                <InheritanceMapV2>
                                    <Entry>
                                        <TemplateName>ResidenceBuilding</TemplateName>
                                        <Index>0</Index>
                                    </Entry>
                                </InheritanceMapV2>
                            </VectorElement>
                        </Item>
                        <Item>
                            <Amount>6</Amount>
                            <Ingredient>1010196</Ingredient>
                            <!--timber-->
                        </Item>
                        <Item>
                            <Amount>2</Amount>
                            <Ingredient>1010205</Ingredient>
                            <!--bricks-->
                        </Item>
                        <Item>
                            <Amount>2</Amount>
                            <Ingredient>1010218</Ingredient>
                            <!--beams-->
                        </Item>
                        <Item>
                            <VectorElement>
                                <InheritedIndex>4</InheritedIndex>
                                <InheritanceMapV2>
                                    <Entry>
                                        <TemplateName>ResidenceBuilding</TemplateName>
                                        <Index>4</Index>
                                    </Entry>
                                </InheritanceMapV2>
                            </VectorElement>
                        </Item>
                        <Item>
                            <VectorElement>
                                <InheritedIndex>5</InheritedIndex>
                                <InheritanceMapV2>
                                    <Entry>
                                        <TemplateName>ResidenceBuilding</TemplateName>
                                        <Index>5</Index>
                                    </Entry>
                                </InheritanceMapV2>
                            </VectorElement>
                        </Item>
                    </UpgradeCost>
                </Upgradable>
                <SoundEmitter>
                    <ConstructionSounds>
                        <BuildSuccessful>
                            <Item>
                                <VectorElement>
                                    <InheritanceMapV2>
                                        <Entry>
                                            <TemplateName>ResidenceBuilding7</TemplateName>
                                            <Index>0</Index>
                                        </Entry>
                                    </InheritanceMapV2>
                                </VectorElement>
                                <Sound>200776</Sound>
                                <!--wwe_sfx_aui_bld_place_bp-->
                            </Item>
                        </BuildSuccessful>
                        <BuildUpgradeFailed>
                            <Item>
                                <Sound>9818387</Sound>
                                <!--wwe_sfx_aui_deny-->
                            </Item>
                        </BuildUpgradeFailed>
                    </ConstructionSounds>
                    <IncidentSounds>
                        <InfectedFire>
                            <Item>
                                <Sound>214659</Sound>
                                <!--wwe_sfx_bld_inc_burn-->
                            </Item>
                        </InfectedFire>
                        <InfectedIllness>
                            <Item>
                                <Sound>214756</Sound>
                                <!--wwe_sfx_vox_inc_ill_os-->
                            </Item>
                        </InfectedIllness>
                        <InfectedRiot>
                            <Item>
                                <Sound>222229</Sound>
                                <!--wwe_sfx_vox_inc_rio_os-->
                            </Item>
                        </InfectedRiot>
                        <ExplosionOneShots>
                            <Item>
                                <Sound>203849</Sound>
                                <!--wwe_sfx_aui_destroy_small-->
                            </Item>
                        </ExplosionOneShots>
                    </IncidentSounds>
                    <BuildingRepaired>
                        <Item>
                            <Sound>203866</Sound>
                            <!--wwe_sfx_aui_bld_3d_renovate-->
                        </Item>
                    </BuildingRepaired>
                    <MaterialType>Wood</MaterialType>
                </SoundEmitter>
                <Infolayer/>
                <FeedbackController/>
                <Residence7>
                    <ResidenceStorage>
                        <InputStorageMax>1</InputStorageMax>
                    </ResidenceStorage>
                    <PopulationLevel7>15000001</PopulationLevel7>
                    <!--Moderate Population 2-->
                    <ResidentMax>20</ResidentMax>
                    <ResidentsRequiredForUpgrade>20</ResidentsRequiredForUpgrade>
                    <IsBaseResidence>1</IsBaseResidence>
                </Residence7>
                <LogisticNode>
                    <REMOVE_THIS_LATER_FeedbackUnitTier>Level2</REMOVE_THIS_LATER_FeedbackUnitTier>
                </LogisticNode>
                <AmbientMoodProvider>
                    <DynamicEnvironmentType>ResidenceT1</DynamicEnvironmentType>
                    <HappinessDependentMurmur>
                        <Angry>
                            <Murmur>WorkerUnhappy</Murmur>
                        </Angry>
                        <Unhappy>
                            <Murmur>WorkerContent</Murmur>
                        </Unhappy>
                        <Neutral>
                            <Murmur>WorkerContent</Murmur>
                        </Neutral>
                        <Happy>
                            <Murmur>WorkerHappy</Murmur>
                        </Happy>
                        <Euphoric>
                            <Murmur>WorkerHappy</Murmur>
                        </Euphoric>
                    </HappinessDependentMurmur>
                </AmbientMoodProvider>
                <UpgradeList/>
                <Attackable>
                    <AttackableType>IslandBuilding</AttackableType>
                    <MaximumHitPoints>2000</MaximumHitPoints>
                </Attackable>
                <IncidentInfectable>
                    <Infectable>
                        <Explosion>
                            <Base>0</Base>
                            <Escalated>0</Escalated>
                        </Explosion>
                    </Infectable>
                    <Explosion>
                        <ExplosionCoreDamage>1000</ExplosionCoreDamage>
                    </Explosion>
                    <IncidentInfectionChanceFactors>
                        <Fire>
                            <BaseChance>4.5</BaseChance>
                            <DensityFactor>0.025</DensityFactor>
                            <DensityDistance>15</DensityDistance>
                        </Fire>
                        <Riot>
                            <ResidenceHappinessFactor>0.4</ResidenceHappinessFactor>
                            <HappinessThreshold>10</HappinessThreshold>
                        </Riot>
                        <Illness>
                            <BaseChance>4.5</BaseChance>
                            <HitpointFactor>0.1</HitpointFactor>
                            <DensityFactor>0.025</DensityFactor>
                            <DensityDistance>15</DensityDistance>
                            <DilapidatedFactor>10</DilapidatedFactor>
                            <FactoryOvertimeFactor>0.3</FactoryOvertimeFactor>
                            <FactoryUndertimeFactor>0.15</FactoryUndertimeFactor>
                            <ResidenceFullOvertimeChance>20</ResidenceFullOvertimeChance>
                            <ResidenceFullUndertimeChance>-15</ResidenceFullUndertimeChance>
                        </Illness>
                        <Explosion>
                            <ResidenceFullOvertimeChance>20</ResidenceFullOvertimeChance>
                            <ResidenceFullUndertimeChance>-15</ResidenceFullUndertimeChance>
                        </Explosion>
                    </IncidentInfectionChanceFactors>
                </IncidentInfectable>
                <Pausable/>
                <Culture/>
                <StreetActivation/>
                <InfluenceSource/>
                <FloorStackOwner/>
                <Maintenance>
                    <IncomeCategory>Skyscrapers</IncomeCategory>
                </Maintenance>
                <Audio>
                    <ClusterEvent>
                        <IsBaseAutoCreateAsset>1</IsBaseAutoCreateAsset>
                        <Values>
                            <AudioLink/>
                        </Values>
                    </ClusterEvent>
                </Audio>
            </Values>
        </Asset>
        <Asset>
            <Template>ResidenceBuilding</Template>
            <Values>
                <Standard>
                    <GUID>1555600003</GUID>
                    <Name>AI_residence_tier03</Name>
                    <IconFilename>data/ui/2kimages/main/3dicons/icon_resident.png</IconFilename>
                    <InfoDescription>163059</InfoDescription>
                    <!--residence 01 infocorner-->
                </Standard>
                <Blocking/>
                <Building>
                    <BuildingType>Residence</BuildingType>
                    <PickingAsset>1555600001</PickingAsset>
                    <!--residence_tier01-->
                    <AssociatedRegions>Moderate</AssociatedRegions>
                </Building>
                <Cost>
                    <Costs>
                        <Item>
                            <VectorElement>
                                <InheritedIndex>0</InheritedIndex>
                                <InheritanceMapV2>
                                    <Entry>
                                        <TemplateName>ResidenceBuilding</TemplateName>
                                        <Index>0</Index>
                                    </Entry>
                                </InheritanceMapV2>
                            </VectorElement>
                        </Item>
                        <Item>
                            <Ingredient>1010196</Ingredient>
                            <!--timber-->
                            <Amount>12</Amount>
                        </Item>
                        <Item>
                            <Ingredient>1010205</Ingredient>
                            <!--bricks-->
                            <Amount>2</Amount>
                        </Item>
                        <Item>
                            <Ingredient>1010218</Ingredient>
                            <!--beams-->
                            <Amount>2</Amount>
                        </Item>
                        <Item>
                            <VectorElement>
                                <InheritedIndex>4</InheritedIndex>
                                <InheritanceMapV2>
                                    <Entry>
                                        <TemplateName>ResidenceBuilding</TemplateName>
                                        <Index>4</Index>
                                    </Entry>
                                </InheritanceMapV2>
                            </VectorElement>
                        </Item>
                        <Item>
                            <VectorElement>
                                <InheritedIndex>5</InheritedIndex>
                                <InheritanceMapV2>
                                    <Entry>
                                        <TemplateName>ResidenceBuilding</TemplateName>
                                        <Index>5</Index>
                                    </Entry>
                                </InheritanceMapV2>
                            </VectorElement>
                        </Item>
                    </Costs>
                </Cost>
                <Mesh/>
                <Object>
                    <Variations>
                        <Item>
                            <Filename>data/graphics/buildings/residence/residence_tier03_estate01/residence_tier03_estate01.cfg</Filename>
                        </Item>
                        <Item>
                            <Filename>data/graphics/buildings/residence/residence_tier03_estate02/residence_tier03_estate02.cfg</Filename>
                        </Item>
                        <Item>
                            <Filename>data/graphics/buildings/residence/residence_tier03_estate03/residence_tier03_estate03.cfg</Filename>
                        </Item>
                        <Item>
                            <Filename>data/graphics/buildings/residence/residence_tier03_estate04/residence_tier03_estate04.cfg</Filename>
                        </Item>
                    </Variations>
                    <Skins>
                        <DefaultSkinName>1010345</DefaultSkinName>
                        <DefaultSkinDescription>23853</DefaultSkinDescription>
                        <!--ChangeBuildingSkin_toDefaultSkinDesc-->
                        <DefaultSkinCategoryName>7312</DefaultSkinCategoryName>
                        <!--Classic-->
                        <OverrideDefaultIcon>data/ui/2kimages/main/3dicons/ornaments/cosmetic_dlc06/icon_tier03_default.png</OverrideDefaultIcon>
                        <SkinList>
                            <Item>
                                <SkinAssetGuid>699</SkinAssetGuid>
                                <!--Skin Residence T03_S01-->
                            </Item>
                            <Item>
                                <SkinAssetGuid>710</SkinAssetGuid>
                                <!--Skin Residence T03_S03-->
                            </Item>
                            <Item>
                                <SkinAssetGuid>718</SkinAssetGuid>
                                <!--Skin Residence T03_S04-->
                            </Item>
                            <Item>
                                <SkinAssetGuid>5248</SkinAssetGuid>
                                <!--CDLC09 Residence Tier03-->
                            </Item>
                            <Item>
                                <SkinAssetGuid>30493</SkinAssetGuid>
                                <!--CDLC13 Residence T3 Skin-->
                            </Item>
                        </SkinList>
                    </Skins>
                </Object>
                <Selection>
                    <OnSelection>
                        <IsBaseAutoCreateAsset>1</IsBaseAutoCreateAsset>
                        <Values>
                            <ActionList/>
                        </Values>
                    </OnSelection>
                    <ParticipantMessageArcheType>Resident_tier03</ParticipantMessageArcheType>
                </Selection>
                <Text>
                    <LocaText>
                        <English>
                            <Text>Artisan Residence</Text>
                            <Status>Exported</Status>
                        </English>
                    </LocaText>
                    <LineID>5229</LineID>
                </Text>
                <Constructable>
                    <ConstructionMenuIcon>15000002</ConstructionMenuIcon>
                    <!--Moderate Population 3-->
                </Constructable>
                <Locked>
                    <DefaultLockedState>0</DefaultLockedState>
                </Locked>
                <Upgradable>
                    <NextGUID>1555600004</NextGUID>
                    <!--residence_tier04-->
                    <UpgradeCost>
                        <Item>
                            <VectorElement>
                                <InheritedIndex>0</InheritedIndex>
                                <InheritanceMapV2>
                                    <Entry>
                                        <TemplateName>ResidenceBuilding</TemplateName>
                                        <Index>0</Index>
                                    </Entry>
                                </InheritanceMapV2>
                            </VectorElement>
                        </Item>
                        <Item>
                            <Amount>8</Amount>
                            <Ingredient>1010196</Ingredient>
                            <!--timber-->
                        </Item>
                        <Item>
                            <Amount>3</Amount>
                            <Ingredient>1010205</Ingredient>
                            <!--bricks-->
                        </Item>
                        <Item>
                            <Amount>2</Amount>
                            <Ingredient>1010218</Ingredient>
                            <!--beams-->
                        </Item>
                        <Item>
                            <Amount>2</Amount>
                            <Ingredient>1010207</Ingredient>
                            <!--window-->
                        </Item>
                        <Item>
                            <VectorElement>
                                <InheritedIndex>5</InheritedIndex>
                                <InheritanceMapV2>
                                    <Entry>
                                        <TemplateName>ResidenceBuilding</TemplateName>
                                        <Index>5</Index>
                                    </Entry>
                                </InheritanceMapV2>
                            </VectorElement>
                        </Item>
                    </UpgradeCost>
                </Upgradable>
                <SoundEmitter>
                    <ConstructionSounds>
                        <BuildSuccessful>
                            <Item>
                                <VectorElement>
                                    <InheritanceMapV2>
                                        <Entry>
                                            <TemplateName>ResidenceBuilding7</TemplateName>
                                            <Index>0</Index>
                                        </Entry>
                                    </InheritanceMapV2>
                                </VectorElement>
                                <Sound>200776</Sound>
                                <!--wwe_sfx_aui_bld_place_bp-->
                            </Item>
                        </BuildSuccessful>
                        <BuildUpgradeFailed>
                            <Item>
                                <Sound>9818387</Sound>
                                <!--wwe_sfx_aui_deny-->
                            </Item>
                        </BuildUpgradeFailed>
                    </ConstructionSounds>
                    <IncidentSounds>
                        <InfectedFire>
                            <Item>
                                <Sound>214659</Sound>
                                <!--wwe_sfx_bld_inc_burn-->
                            </Item>
                        </InfectedFire>
                        <InfectedIllness>
                            <Item>
                                <Sound>214756</Sound>
                                <!--wwe_sfx_vox_inc_ill_os-->
                            </Item>
                        </InfectedIllness>
                        <InfectedRiot>
                            <Item>
                                <Sound>222229</Sound>
                                <!--wwe_sfx_vox_inc_rio_os-->
                            </Item>
                        </InfectedRiot>
                        <ExplosionOneShots>
                            <Item>
                                <Sound>203849</Sound>
                                <!--wwe_sfx_aui_destroy_small-->
                            </Item>
                        </ExplosionOneShots>
                    </IncidentSounds>
                    <BuildingRepaired>
                        <Item>
                            <Sound>203866</Sound>
                            <!--wwe_sfx_aui_bld_3d_renovate-->
                        </Item>
                    </BuildingRepaired>
                    <MaterialType>Stone</MaterialType>
                </SoundEmitter>
                <Infolayer/>
                <FeedbackController/>
                <Residence7>
                    <ResidenceStorage>
                        <InputStorageMax>1</InputStorageMax>
                    </ResidenceStorage>
                    <PopulationLevel7>15000002</PopulationLevel7>
                    <!--Moderate Population 3-->
                    <ResidentMax>30</ResidentMax>
                    <ResidentsRequiredForUpgrade>30</ResidentsRequiredForUpgrade>
                    <ResidentsOccupancyThresholdMax>0.25</ResidentsOccupancyThresholdMax>
                    <IsBaseResidence>1</IsBaseResidence>
                </Residence7>
                <LogisticNode>
                    <REMOVE_THIS_LATER_FeedbackUnitTier>Level3</REMOVE_THIS_LATER_FeedbackUnitTier>
                </LogisticNode>
                <AmbientMoodProvider>
                    <AmbientMood>ResidenceTier3</AmbientMood>
                    <DynamicEnvironmentType>ResidenceT5</DynamicEnvironmentType>
                    <HappinessDependentMurmur>
                        <Angry>
                            <Murmur>ArtisanUnhappy</Murmur>
                        </Angry>
                        <Unhappy>
                            <Murmur>ArtisanContent</Murmur>
                        </Unhappy>
                        <Neutral>
                            <Murmur>ArtisanContent</Murmur>
                        </Neutral>
                        <Happy>
                            <Murmur>ArtisanHappy</Murmur>
                        </Happy>
                        <Euphoric>
                            <Murmur>ArtisanHappy</Murmur>
                        </Euphoric>
                    </HappinessDependentMurmur>
                </AmbientMoodProvider>
                <UpgradeList/>
                <Attackable>
                    <AttackableType>IslandBuilding</AttackableType>
                    <MaximumHitPoints>2500</MaximumHitPoints>
                </Attackable>
                <IncidentInfectable>
                    <Infectable>
                        <Explosion>
                            <Base>0</Base>
                            <Escalated>0</Escalated>
                        </Explosion>
                    </Infectable>
                    <Explosion>
                        <ExplosionCoreDamage>1000</ExplosionCoreDamage>
                    </Explosion>
                    <IncidentInfectionChanceFactors>
                        <Fire>
                            <BaseChance>4</BaseChance>
                            <DensityFactor>0.025</DensityFactor>
                            <DensityDistance>15</DensityDistance>
                        </Fire>
                        <Riot>
                            <ResidenceHappinessFactor>0.4</ResidenceHappinessFactor>
                            <HappinessThreshold>10</HappinessThreshold>
                        </Riot>
                        <Illness>
                            <BaseChance>5</BaseChance>
                            <HitpointFactor>0.1</HitpointFactor>
                            <DensityFactor>0.025</DensityFactor>
                            <DensityDistance>15</DensityDistance>
                            <DilapidatedFactor>10</DilapidatedFactor>
                            <FactoryOvertimeFactor>0.3</FactoryOvertimeFactor>
                            <FactoryUndertimeFactor>0.15</FactoryUndertimeFactor>
                            <ResidenceFullOvertimeChance>20</ResidenceFullOvertimeChance>
                            <ResidenceFullUndertimeChance>-15</ResidenceFullUndertimeChance>
                        </Illness>
                        <Explosion>
                            <ResidenceFullOvertimeChance>20</ResidenceFullOvertimeChance>
                            <ResidenceFullUndertimeChance>-15</ResidenceFullUndertimeChance>
                        </Explosion>
                    </IncidentInfectionChanceFactors>
                </IncidentInfectable>
                <Pausable/>
                <Culture/>
                <StreetActivation/>
                <InfluenceSource/>
                <FloorStackOwner/>
                <Maintenance>
                    <IncomeCategory>Skyscrapers</IncomeCategory>
                </Maintenance>
                <Audio>
                    <ClusterEvent>
                        <IsBaseAutoCreateAsset>1</IsBaseAutoCreateAsset>
                        <Values>
                            <AudioLink/>
                        </Values>
                    </ClusterEvent>
                </Audio>
            </Values>
        </Asset>
        <Asset>
            <Template>ResidenceBuilding</Template>
            <Values>
                <Standard>
                    <GUID>1555600004</GUID>
                    <Name>AI_residence_tier04</Name>
                    <IconFilename>data/ui/2kimages/main/3dicons/icon_resident.png</IconFilename>
                    <InfoDescription>163059</InfoDescription>
                    <!--residence 01 infocorner-->
                </Standard>
                <Blocking/>
                <Building>
                    <BuildingType>Residence</BuildingType>
                    <PickingAsset>1555600001</PickingAsset>
                    <!--residence_tier01-->
                    <InfluencedByNeighbors>
                        <Item>
                            <Building>1010345</Building>
                            <!--residence_tier03-->
                        </Item>
                        <Item>
                            <Building>1010346</Building>
                        </Item>
                        <Item>
                            <Building>1010347</Building>
                            <!--residence_tier05-->
                        </Item>
                        <Item>
                            <Building>1010344</Building>
                            <!--residence_tier02-->
                        </Item>
                        <Item>
                            <Building>1010343</Building>
                            <!--residence_tier01-->
                        </Item>
                        <Item>
                            <Building>601888</Building>
                            <!--residence_tier04_level01-->
                        </Item>
                        <Item>
                            <Building>601889</Building>
                            <!--residence_tier04_level02-->
                        </Item>
                        <Item>
                            <Building>601890</Building>
                            <!--residence_tier04_level03-->
                        </Item>
                        <Item>
                            <Building>601882</Building>
                            <!--residence_tier05_level01-->
                        </Item>
                        <Item>
                            <Building>601883</Building>
                            <!--residence_tier05_level02-->
                        </Item>
                        <Item>
                            <Building>601884</Building>
                            <!--residence_tier05_level03-->
                        </Item>
                        <Item>
                            <Building>601886</Building>
                            <!--residence_tier05_level04-->
                        </Item>
                        <Item>
                            <Building>601891</Building>
                            <!--residence_tier05_level05-->
                        </Item>
                    </InfluencedByNeighbors>
                    <AssociatedRegions>Moderate</AssociatedRegions>
                    <BuildingBlockPool>
                        <DontCare>
                            <Pool>
                                <Item>
                                    <Variation>4</Variation>
                                </Item>
                                <Item>
                                    <DirectionOffet>1</DirectionOffet>
                                    <Variation>5</Variation>
                                </Item>
                                <Item>
                                    <DirectionOffet>2</DirectionOffet>
                                    <Variation>6</Variation>
                                </Item>
                                <Item>
                                    <DirectionOffet>3</DirectionOffet>
                                    <Variation>7</Variation>
                                </Item>
                                <Item>
                                    <DirectionOffet>1</DirectionOffet>
                                    <Variation>1</Variation>
                                </Item>
                                <Item>
                                    <DirectionOffet>2</DirectionOffet>
                                    <Variation>2</Variation>
                                </Item>
                                <Item>
                                    <DirectionOffet>3</DirectionOffet>
                                    <Variation>3</Variation>
                                </Item>
                            </Pool>
                        </DontCare>
                        <Corner>
                            <Pool>
                                <Item>
                                </Item>
                                <Item>
                                    <DirectionOffet>2</DirectionOffet>
                                    <Variation>1</Variation>
                                </Item>
                                <Item>
                                    <Variation>2</Variation>
                                </Item>
                            </Pool>
                        </Corner>
                        <Mid>
                            <Pool>
                                <Item>
                                    <Variation>3</Variation>
                                </Item>
                                <Item>
                                    <Variation>4</Variation>
                                </Item>
                                <Item>
                                    <Variation>5</Variation>
                                </Item>
                                <Item>
                                    <Variation>6</Variation>
                                </Item>
                                <Item>
                                    <DirectionOffet>2</DirectionOffet>
                                    <Variation>3</Variation>
                                </Item>
                                <Item>
                                    <DirectionOffet>2</DirectionOffet>
                                    <Variation>4</Variation>
                                </Item>
                                <Item>
                                    <DirectionOffet>2</DirectionOffet>
                                    <Variation>5</Variation>
                                </Item>
                                <Item>
                                    <DirectionOffet>2</DirectionOffet>
                                    <Variation>6</Variation>
                                </Item>
                                <Item>
                                    <DirectionOffet>1</DirectionOffet>
                                    <Variation>7</Variation>
                                </Item>
                            </Pool>
                        </Mid>
                    </BuildingBlockPool>
                </Building>
                <Cost>
                    <Costs>
                        <Item>
                            <VectorElement>
                                <InheritedIndex>0</InheritedIndex>
                                <InheritanceMapV2>
                                    <Entry>
                                        <TemplateName>ResidenceBuilding</TemplateName>
                                        <Index>0</Index>
                                    </Entry>
                                </InheritanceMapV2>
                            </VectorElement>
                        </Item>
                        <Item>
                            <Ingredient>1010196</Ingredient>
                            <!--timber-->
                            <Amount>20</Amount>
                        </Item>
                        <Item>
                            <Ingredient>1010205</Ingredient>
                            <!--bricks-->
                            <Amount>5</Amount>
                        </Item>
                        <Item>
                            <Ingredient>1010218</Ingredient>
                            <!--beams-->
                            <Amount>4</Amount>
                        </Item>
                        <Item>
                            <Ingredient>1010207</Ingredient>
                            <!--window-->
                            <Amount>2</Amount>
                        </Item>
                        <Item>
                            <VectorElement>
                                <InheritedIndex>5</InheritedIndex>
                                <InheritanceMapV2>
                                    <Entry>
                                        <TemplateName>ResidenceBuilding</TemplateName>
                                        <Index>5</Index>
                                    </Entry>
                                </InheritanceMapV2>
                            </VectorElement>
                        </Item>
                    </Costs>
                </Cost>
                <Mesh/>
                <Object>
                    <Variations>
                        <Item>
                            <Filename>data/graphics/buildings/residence/residence_tier04_01/residence_tier04_01.cfg</Filename>
                        </Item>
                        <Item>
                            <Filename>data/graphics/buildings/residence/residence_tier04_02/residence_tier04_02.cfg</Filename>
                        </Item>
                        <Item>
                            <Filename>data/graphics/buildings/residence/residence_tier04_03/residence_tier04_03.cfg</Filename>
                        </Item>
                        <Item>
                            <Filename>data/graphics/buildings/residence/residence_tier04_04/residence_tier04_04.cfg</Filename>
                        </Item>
                        <Item>
                            <Filename>data/graphics/buildings/residence/residence_tier04_05/residence_tier04_05.cfg</Filename>
                        </Item>
                        <Item>
                            <Filename>data/graphics/buildings/residence/residence_tier04_06/residence_tier04_06.cfg</Filename>
                        </Item>
                        <Item>
                            <Filename>data/graphics/buildings/residence/residence_tier04_07/residence_tier04_07.cfg</Filename>
                        </Item>
                        <Item>
                            <Filename>data/graphics/buildings/residence/residence_tier04_08/residence_tier04_08.cfg</Filename>
                        </Item>
                    </Variations>
                    <Skins>
                        <DefaultSkinName>1010346</DefaultSkinName>
                        <DefaultSkinDescription>23853</DefaultSkinDescription>
                        <!--ChangeBuildingSkin_toDefaultSkinDesc-->
                        <DefaultSkinCategoryName>7312</DefaultSkinCategoryName>
                        <!--Classic-->
                        <OverrideDefaultIcon>data/ui/2kimages/main/3dicons/ornaments/cosmetic_dlc06/icon_tier04_default.png</OverrideDefaultIcon>
                        <SkinList>
                            <Item>
                                <SkinAssetGuid>700</SkinAssetGuid>
                                <!--Skin Residence T04_S01-->
                            </Item>
                            <Item>
                                <SkinAssetGuid>722</SkinAssetGuid>
                                <!--Skin Residence T04_S02-->
                            </Item>
                            <Item>
                                <SkinAssetGuid>711</SkinAssetGuid>
                                <!--Skin Residence T04_S03-->
                            </Item>
                        </SkinList>
                    </Skins>
                </Object>
                <Selection>
                    <OnSelection>
                        <IsBaseAutoCreateAsset>1</IsBaseAutoCreateAsset>
                        <Values>
                            <ActionList/>
                        </Values>
                    </OnSelection>
                    <ParticipantMessageArcheType>Resident_tier04</ParticipantMessageArcheType>
                </Selection>
                <Text>
                    <LocaText>
                        <English>
                            <Text>Engineer Residence</Text>
                            <Status>Exported</Status>
                        </English>
                    </LocaText>
                    <LineID>5230</LineID>
                </Text>
                <Constructable>
                    <ConstructionMenuIcon>15000003</ConstructionMenuIcon>
                    <!--Moderate Population 4-->
                </Constructable>
                <Locked>
                    <DefaultLockedState>0</DefaultLockedState>
                </Locked>
                <Upgradable>
                    <NextGUID>1555600005</NextGUID>
                    <!--residence_tier05-->
                    <UpgradeCost>
                        <Item>
                            <VectorElement>
                                <InheritedIndex>0</InheritedIndex>
                                <InheritanceMapV2>
                                    <Entry>
                                        <TemplateName>ResidenceBuilding</TemplateName>
                                        <Index>0</Index>
                                    </Entry>
                                </InheritanceMapV2>
                            </VectorElement>
                        </Item>
                        <Item>
                            <Amount>10</Amount>
                            <Ingredient>1010196</Ingredient>
                            <!--timber-->
                        </Item>
                        <Item>
                            <Amount>4</Amount>
                            <Ingredient>1010205</Ingredient>
                            <!--bricks-->
                        </Item>
                        <Item>
                            <Amount>3</Amount>
                            <Ingredient>1010218</Ingredient>
                            <!--beams-->
                        </Item>
                        <Item>
                            <Amount>3</Amount>
                            <Ingredient>1010207</Ingredient>
                            <!--window-->
                        </Item>
                        <Item>
                            <Amount>3</Amount>
                            <Ingredient>1010202</Ingredient>
                            <!--concrete-->
                        </Item>
                    </UpgradeCost>
                </Upgradable>
                <SoundEmitter>
                    <ConstructionSounds>
                        <BuildSuccessful>
                            <Item>
                                <VectorElement>
                                    <InheritanceMapV2>
                                        <Entry>
                                            <TemplateName>ResidenceBuilding7</TemplateName>
                                            <Index>0</Index>
                                        </Entry>
                                    </InheritanceMapV2>
                                </VectorElement>
                                <Sound>200776</Sound>
                                <!--wwe_sfx_aui_bld_place_bp-->
                            </Item>
                        </BuildSuccessful>
                        <BuildUpgradeFailed>
                            <Item>
                                <Sound>9818387</Sound>
                                <!--wwe_sfx_aui_deny-->
                            </Item>
                        </BuildUpgradeFailed>
                    </ConstructionSounds>
                    <IncidentSounds>
                        <InfectedFire>
                            <Item>
                                <Sound>214659</Sound>
                                <!--wwe_sfx_bld_inc_burn-->
                            </Item>
                        </InfectedFire>
                        <InfectedIllness>
                            <Item>
                                <Sound>214756</Sound>
                                <!--wwe_sfx_vox_inc_ill_os-->
                            </Item>
                        </InfectedIllness>
                        <InfectedRiot>
                            <Item>
                                <Sound>222229</Sound>
                                <!--wwe_sfx_vox_inc_rio_os-->
                            </Item>
                        </InfectedRiot>
                        <ExplosionOneShots>
                            <Item>
                                <Sound>203849</Sound>
                                <!--wwe_sfx_aui_destroy_small-->
                            </Item>
                        </ExplosionOneShots>
                    </IncidentSounds>
                    <BuildingRepaired>
                        <Item>
                            <Sound>203866</Sound>
                            <!--wwe_sfx_aui_bld_3d_renovate-->
                        </Item>
                    </BuildingRepaired>
                    <MaterialType>Stone</MaterialType>
                </SoundEmitter>
                <Infolayer/>
                <FeedbackController/>
                <Residence7>
                    <ResidenceStorage>
                        <InputStorageMax>1</InputStorageMax>
                    </ResidenceStorage>
                    <PopulationLevel7>15000003</PopulationLevel7>
                    <!--Moderate Population 4-->
                    <ResidentMax>40</ResidentMax>
                    <ResidentsRequiredForUpgrade>40</ResidentsRequiredForUpgrade>
                    <IsBaseResidence>1</IsBaseResidence>
                </Residence7>
                <LogisticNode>
                    <REMOVE_THIS_LATER_FeedbackUnitTier>Level4</REMOVE_THIS_LATER_FeedbackUnitTier>
                </LogisticNode>
                <AmbientMoodProvider>
                    <AmbientMood>ResidenceTier5</AmbientMood>
                    <DynamicEnvironmentType>ResidenceT5</DynamicEnvironmentType>
                    <HappinessDependentMurmur>
                        <Angry>
                            <Murmur>EngineerUnhappy</Murmur>
                        </Angry>
                        <Unhappy>
                            <Murmur>EngineerContent</Murmur>
                        </Unhappy>
                        <Neutral>
                            <Murmur>EngineerContent</Murmur>
                        </Neutral>
                        <Happy>
                            <Murmur>EngineerHappy</Murmur>
                        </Happy>
                        <Euphoric>
                            <Murmur>EngineerHappy</Murmur>
                        </Euphoric>
                    </HappinessDependentMurmur>
                </AmbientMoodProvider>
                <UpgradeList/>
                <Attackable>
                    <AttackableType>IslandBuilding</AttackableType>
                    <MaximumHitPoints>3000</MaximumHitPoints>
                </Attackable>
                <IncidentInfectable>
                    <Infectable>
                        <Explosion>
                            <Base>0</Base>
                            <Escalated>0</Escalated>
                        </Explosion>
                    </Infectable>
                    <Explosion>
                        <ExplosionCoreDamage>1000</ExplosionCoreDamage>
                    </Explosion>
                    <IncidentInfectionChanceFactors>
                        <Fire>
                            <BaseChance>3.5</BaseChance>
                            <DensityFactor>0.025</DensityFactor>
                            <DensityDistance>15</DensityDistance>
                        </Fire>
                        <Riot>
                            <ResidenceHappinessFactor>0.4</ResidenceHappinessFactor>
                            <HappinessThreshold>10</HappinessThreshold>
                        </Riot>
                        <Illness>
                            <BaseChance>3.5</BaseChance>
                            <HitpointFactor>0.1</HitpointFactor>
                            <DensityFactor>0.025</DensityFactor>
                            <DensityDistance>15</DensityDistance>
                            <DilapidatedFactor>10</DilapidatedFactor>
                            <FactoryOvertimeFactor>0.3</FactoryOvertimeFactor>
                            <FactoryUndertimeFactor>0.15</FactoryUndertimeFactor>
                            <ResidenceFullOvertimeChance>20</ResidenceFullOvertimeChance>
                            <ResidenceFullUndertimeChance>-15</ResidenceFullUndertimeChance>
                        </Illness>
                        <Explosion>
                            <ResidenceFullOvertimeChance>20</ResidenceFullOvertimeChance>
                            <ResidenceFullUndertimeChance>-15</ResidenceFullUndertimeChance>
                        </Explosion>
                    </IncidentInfectionChanceFactors>
                </IncidentInfectable>
                <Pausable/>
                <Culture/>
                <StreetActivation/>
                <InfluenceSource>
                    <InfluenceSource>Engineers</InfluenceSource>
                </InfluenceSource>
 <!--               <FloorStackOwner>
                    <UpgradeTargetGUID>601888</UpgradeTargetGUID>
                    <AddFloorCost>
                        <Item>
                            <Ingredient>1010017</Ingredient>
                            <Amount>500</Amount>
                        </Item>
                        <Item>
                            <Ingredient>1010196</Ingredient>
                            <Amount>10</Amount>
                        </Item>
                        <Item>
                            <Ingredient>1010205</Ingredient>
                            <Amount>5</Amount>
                        </Item>
                        <Item>
                            <Ingredient>1010218</Ingredient>
                            <Amount>10</Amount>
                        </Item>
                        <Item>
                            <Ingredient>1010207</Ingredient>
                            <Amount>5</Amount>
                        </Item>
                        <Item>
                            <Ingredient>1010202</Ingredient>
                            <Amount>5</Amount>
                        </Item>
                        <Item>
                            <Ingredient>134623</Ingredient>
                            Elevator
                            <Amount>2</Amount>
                        </Item>
                    </AddFloorCost>
                </FloorStackOwner> -->
                <Maintenance>
                    <IncomeCategory>Skyscrapers</IncomeCategory>
                </Maintenance>
                <Audio>
                    <ClusterEvent>
                        <IsBaseAutoCreateAsset>1</IsBaseAutoCreateAsset>
                        <Values>
                            <AudioLink/>
                        </Values>
                    </ClusterEvent>
                </Audio>
            </Values>
        </Asset>
        <Asset>
            <Template>ResidenceBuilding</Template>
            <Values>
                <Standard>
                    <GUID>1555600005</GUID>
                    <Name>AI_residence_tier05</Name>
                    <IconFilename>data/ui/2kimages/main/3dicons/icon_resident.png</IconFilename>
                    <ID>ResidenceTier5</ID>
                    <InfoDescription>163059</InfoDescription>
                    <!--residence 01 infocorner-->
                </Standard>
                <Blocking/>
                <Building>
                    <BuildingType>Residence</BuildingType>
                    <PickingAsset>1555600001</PickingAsset>
                    <!--residence_tier01-->
                    <InfluencedByNeighbors>
                        <Item>
                            <Building>1010345</Building>
                            <!--residence_tier03-->
                        </Item>
                        <Item>
                            <Building>1010346</Building>
                            <!--residence_tier04-->
                        </Item>
                        <Item>
                            <Building>1010347</Building>
                        </Item>
                        <Item>
                            <Building>1010344</Building>
                            <!--residence_tier02-->
                        </Item>
                        <Item>
                            <Building>1010343</Building>
                            <!--residence_tier01-->
                        </Item>
                        <Item>
                            <Building>601888</Building>
                            <!--residence_tier04_level01-->
                        </Item>
                        <Item>
                            <Building>601889</Building>
                            <!--residence_tier04_level02-->
                        </Item>
                        <Item>
                            <Building>601890</Building>
                            <!--residence_tier04_level03-->
                        </Item>
                        <Item>
                            <Building>601882</Building>
                            <!--residence_tier05_level01-->
                        </Item>
                        <Item>
                            <Building>601883</Building>
                            <!--residence_tier05_level02-->
                        </Item>
                        <Item>
                            <Building>601884</Building>
                            <!--residence_tier05_level03-->
                        </Item>
                        <Item>
                            <Building>601886</Building>
                            <!--residence_tier05_level04-->
                        </Item>
                        <Item>
                            <Building>601891</Building>
                            <!--residence_tier05_level05-->
                        </Item>
                    </InfluencedByNeighbors>
                    <AssociatedRegions>Moderate</AssociatedRegions>
                    <BuildingBlockPool>
                        <DontCare>
                            <Pool>
                                <Item>
                                </Item>
                                <Item>
                                    <DirectionOffet>1</DirectionOffet>
                                    <Variation>1</Variation>
                                </Item>
                                <Item>
                                    <DirectionOffet>2</DirectionOffet>
                                    <Variation>2</Variation>
                                </Item>
                                <Item>
                                    <DirectionOffet>1</DirectionOffet>
                                    <Variation>3</Variation>
                                </Item>
                                <Item>
                                    <DirectionOffet>3</DirectionOffet>
                                    <Variation>4</Variation>
                                </Item>
                                <Item>
                                    <DirectionOffet>1</DirectionOffet>
                                    <Variation>5</Variation>
                                </Item>
                                <Item>
                                    <DirectionOffet>3</DirectionOffet>
                                    <Variation>6</Variation>
                                </Item>
                            </Pool>
                        </DontCare>
                        <Corner>
                            <Pool>
                                <Item>
                                    <Variation>1</Variation>
                                </Item>
                                <Item>
                                    <DirectionOffet>3</DirectionOffet>
                                </Item>
                                <Item>
                                    <DirectionOffet>3</DirectionOffet>
                                    <Variation>2</Variation>
                                </Item>
                            </Pool>
                        </Corner>
                        <Mid>
                            <Pool>
                                <Item>
                                    <Variation>4</Variation>
                                </Item>
                                <Item>
                                    <DirectionOffet>1</DirectionOffet>
                                    <Variation>3</Variation>
                                </Item>
                                <Item>
                                    <DirectionOffet>1</DirectionOffet>
                                    <Variation>5</Variation>
                                </Item>
                                <Item>
                                    <DirectionOffet>3</DirectionOffet>
                                    <Variation>3</Variation>
                                </Item>
                                <Item>
                                    <DirectionOffet>2</DirectionOffet>
                                    <Variation>4</Variation>
                                </Item>
                                <Item>
                                    <DirectionOffet>3</DirectionOffet>
                                    <Variation>5</Variation>
                                </Item>
                            </Pool>
                        </Mid>
                    </BuildingBlockPool>
                </Building>
                <Cost>
                    <Costs>
                        <Item>
                            <VectorElement>
                                <InheritedIndex>0</InheritedIndex>
                                <InheritanceMapV2>
                                    <Entry>
                                        <TemplateName>ResidenceBuilding</TemplateName>
                                        <Index>0</Index>
                                    </Entry>
                                </InheritanceMapV2>
                            </VectorElement>
                        </Item>
                        <Item>
                            <Ingredient>1010196</Ingredient>
                            <!--timber-->
                            <Amount>30</Amount>
                        </Item>
                        <Item>
                            <Ingredient>1010205</Ingredient>
                            <!--bricks-->
                            <Amount>9</Amount>
                        </Item>
                        <Item>
                            <Ingredient>1010218</Ingredient>
                            <!--beams-->
                            <Amount>7</Amount>
                        </Item>
                        <Item>
                            <Ingredient>1010207</Ingredient>
                            <!--window-->
                            <Amount>5</Amount>
                        </Item>
                        <Item>
                            <Ingredient>1010202</Ingredient>
                            <!--concrete-->
                            <Amount>3</Amount>
                        </Item>
                    </Costs>
                </Cost>
                <Mesh>
                    <SkyDayListener>1</SkyDayListener>
                </Mesh>
                <Object>
                    <Variations>
                        <Item>
                            <Filename>data/graphics/buildings/residence/residence_tier05_01/residence_tier05_01.cfg</Filename>
                        </Item>
                        <Item>
                            <Filename>data/graphics/buildings/residence/residence_tier05_02/residence_tier05_02.cfg</Filename>
                        </Item>
                        <Item>
                            <Filename>data/graphics/buildings/residence/residence_tier05_03/residence_tier05_03.cfg</Filename>
                        </Item>
                        <Item>
                            <Filename>data/graphics/buildings/residence/residence_tier05_04/residence_tier05_04.cfg</Filename>
                        </Item>
                        <Item>
                            <Filename>data/graphics/buildings/residence/residence_tier05_05/residence_tier05_05.cfg</Filename>
                        </Item>
                        <Item>
                            <Filename>data/graphics/buildings/residence/residence_tier05_06/residence_tier05_06.cfg</Filename>
                        </Item>
                        <Item>
                            <Filename>data/graphics/buildings/residence/residence_tier05_07/residence_tier05_07.cfg</Filename>
                        </Item>
                    </Variations>
                    <Skins>
                        <DefaultSkinName>1010347</DefaultSkinName>
                        <DefaultSkinDescription>23853</DefaultSkinDescription>
                        <!--ChangeBuildingSkin_toDefaultSkinDesc-->
                        <DefaultSkinCategoryName>7312</DefaultSkinCategoryName>
                        <!--Classic-->
                        <OverrideDefaultIcon>data/ui/2kimages/main/3dicons/ornaments/cosmetic_dlc06/icon_tier05_default.png</OverrideDefaultIcon>
                        <SkinList>
                            <Item>
                                <SkinAssetGuid>701</SkinAssetGuid>
                                <!--Skin Residence T05_S01-->
                            </Item>
                            <Item>
                                <SkinAssetGuid>723</SkinAssetGuid>
                                <!--Skin Residence T05_S02-->
                            </Item>
                            <Item>
                                <SkinAssetGuid>712</SkinAssetGuid>
                                <!--Skin Residence T05_S03-->
                            </Item>
                        </SkinList>
                    </Skins>
                </Object>
                <Selection>
                    <OnSelection>
                        <IsBaseAutoCreateAsset>1</IsBaseAutoCreateAsset>
                        <Values>
                            <ActionList/>
                        </Values>
                    </OnSelection>
                    <ParticipantMessageArcheType>Resident_tier05</ParticipantMessageArcheType>
                </Selection>
                <Text>
                    <LocaText>
                        <English>
                            <Text>Investor Residence</Text>
                            <Status>Exported</Status>
                        </English>
                    </LocaText>
                    <LineID>5231</LineID>
                </Text>
                <Constructable>
                    <ConstructionMenuIcon>15000004</ConstructionMenuIcon>
                    <!--Moderate Population 5-->
                </Constructable>
                <Locked>
                    <DefaultLockedState>0</DefaultLockedState>
                </Locked>
                <Upgradable>
                    <UpgradeCost/>
                </Upgradable>
                <SoundEmitter>
                    <ConstructionSounds>
                        <BuildSuccessful>
                            <Item>
                                <VectorElement>
                                    <InheritanceMapV2>
                                        <Entry>
                                            <TemplateName>ResidenceBuilding7</TemplateName>
                                            <Index>0</Index>
                                        </Entry>
                                    </InheritanceMapV2>
                                </VectorElement>
                                <Sound>200776</Sound>
                                <!--wwe_sfx_aui_bld_place_bp-->
                            </Item>
                        </BuildSuccessful>
                        <BuildUpgradeFailed>
                            <Item>
                                <Sound>9818387</Sound>
                                <!--wwe_sfx_aui_deny-->
                            </Item>
                        </BuildUpgradeFailed>
                    </ConstructionSounds>
                    <IncidentSounds>
                        <InfectedFire>
                            <Item>
                                <Sound>214659</Sound>
                                <!--wwe_sfx_bld_inc_burn-->
                            </Item>
                        </InfectedFire>
                        <InfectedIllness>
                            <Item>
                                <Sound>214756</Sound>
                                <!--wwe_sfx_vox_inc_ill_os-->
                            </Item>
                        </InfectedIllness>
                        <InfectedRiot>
                            <Item>
                                <Sound>222229</Sound>
                                <!--wwe_sfx_vox_inc_rio_os-->
                            </Item>
                        </InfectedRiot>
                        <ExplosionOneShots>
                            <Item>
                                <Sound>203849</Sound>
                                <!--wwe_sfx_aui_destroy_small-->
                            </Item>
                        </ExplosionOneShots>
                    </IncidentSounds>
                    <BuildingRepaired>
                        <Item>
                            <Sound>203866</Sound>
                            <!--wwe_sfx_aui_bld_3d_renovate-->
                        </Item>
                    </BuildingRepaired>
                    <MaterialType>Stone</MaterialType>
                </SoundEmitter>
                <Infolayer/>
                <FeedbackController/>
                <Residence7>
                    <ResidenceStorage>
                        <InputStorageMax>1</InputStorageMax>
                    </ResidenceStorage>
                    <PopulationLevel7>15000004</PopulationLevel7>
                    <!--Moderate Population 5-->
                    <ResidentMax>50</ResidentMax>
                    <ResidentsRequiredForUpgrade>50</ResidentsRequiredForUpgrade>
                    <IsBaseResidence>1</IsBaseResidence>
                </Residence7>
                <LogisticNode>
                    <REMOVE_THIS_LATER_FeedbackUnitTier>Level4</REMOVE_THIS_LATER_FeedbackUnitTier>
                </LogisticNode>
                <AmbientMoodProvider>
                    <AmbientMood>ResidenceTier5</AmbientMood>
                    <DynamicEnvironmentType>ResidenceT5</DynamicEnvironmentType>
                    <HappinessDependentMurmur>
                        <Angry>
                            <Murmur>InvestorUnhappy</Murmur>
                        </Angry>
                        <Unhappy>
                            <Murmur>InvestorContent</Murmur>
                        </Unhappy>
                        <Neutral>
                            <Murmur>InvestorContent</Murmur>
                        </Neutral>
                        <Happy>
                            <Murmur>InvestorHappy</Murmur>
                        </Happy>
                        <Euphoric>
                            <Murmur>InvestorHappy</Murmur>
                        </Euphoric>
                    </HappinessDependentMurmur>
                </AmbientMoodProvider>
                <UpgradeList/>
                <Attackable>
                    <AttackableType>IslandBuilding</AttackableType>
                    <MaximumHitPoints>3500</MaximumHitPoints>
                </Attackable>
                <IncidentInfectable>
                    <Infectable>
                        <Explosion>
                            <Base>0</Base>
                            <Escalated>0</Escalated>
                        </Explosion>
                    </Infectable>
                    <Explosion>
                        <ExplosionCoreDamage>1000</ExplosionCoreDamage>
                    </Explosion>
                    <IncidentInfectionChanceFactors>
                        <Fire>
                            <BaseChance>3</BaseChance>
                            <DensityFactor>0.025</DensityFactor>
                            <DensityDistance>15</DensityDistance>
                        </Fire>
                        <Riot>
                            <ResidenceHappinessFactor>0.4</ResidenceHappinessFactor>
                            <HappinessThreshold>10</HappinessThreshold>
                        </Riot>
                        <Illness>
                            <BaseChance>3</BaseChance>
                            <HitpointFactor>0.1</HitpointFactor>
                            <DensityFactor>0.025</DensityFactor>
                            <DensityDistance>15</DensityDistance>
                            <DilapidatedFactor>10</DilapidatedFactor>
                            <FactoryOvertimeFactor>0.3</FactoryOvertimeFactor>
                            <FactoryUndertimeFactor>0.15</FactoryUndertimeFactor>
                            <ResidenceFullOvertimeChance>20</ResidenceFullOvertimeChance>
                            <ResidenceFullUndertimeChance>-15</ResidenceFullUndertimeChance>
                        </Illness>
                        <Explosion>
                            <ResidenceFullOvertimeChance>20</ResidenceFullOvertimeChance>
                            <ResidenceFullUndertimeChance>-15</ResidenceFullUndertimeChance>
                        </Explosion>
                    </IncidentInfectionChanceFactors>
                </IncidentInfectable>
                <Pausable/>
                <Culture/>
                <StreetActivation/>
                <InfluenceSource>
                    <InfluenceSource>Investors</InfluenceSource>
                    <ProvidesDifficultyInfluence>1</ProvidesDifficultyInfluence>
                </InfluenceSource>
<!--                <FloorStackOwner>
                    <UpgradeTargetGUID>601882</UpgradeTargetGUID>
                    residence_tier05_level01
                    <AddFloorCost>
                        <Item>
                            <Ingredient>1010017</Ingredient>
                            <Amount>1000</Amount>
                        </Item>
                        <Item>
                            <Ingredient>1010196</Ingredient>
                            <Amount>10</Amount>
                        </Item>
                        <Item>
                            <Ingredient>1010205</Ingredient>
                            <Amount>5</Amount>
                        </Item>
                        <Item>
                            <Ingredient>1010218</Ingredient>
                            <Amount>15</Amount>
                        </Item>
                        <Item>
                            <Ingredient>1010207</Ingredient>
                            <Amount>10</Amount>
                        </Item>
                        <Item>
                            <Ingredient>1010202</Ingredient>
                            <Amount>5</Amount>
                        </Item>
                        <Item>
                            <Ingredient>134623</Ingredient>
                            <Amount>5</Amount>
                        </Item>
                    </AddFloorCost>
                </FloorStackOwner> -->
                <Maintenance>
                    <IncomeCategory>Skyscrapers</IncomeCategory>
                </Maintenance>
                <Audio>
                    <ClusterEvent>
                        <IsBaseAutoCreateAsset>1</IsBaseAutoCreateAsset>
                        <Values>
                            <AudioLink/>
                        </Values>
                    </ClusterEvent>
                </Audio>
            </Values>
        </Asset>
    </ModOp>

    <ModOp Type="Add" GUID="167" Path="/Values/ConstructionAI/">
        <BuildingReplacements>
            <Item>
                <Building>1010343</Building>
                <!--Residence_tier01-->
                <Replacement>1555600001</Replacement>
                <!--AI_Residence_tier01-->
            </Item>
            <Item>
                <Building>1010344</Building>
                <!--Residence_tier01-->
                <Replacement>1555600002</Replacement>
                <!--AI_Residence_tier01-->
            </Item>
            <Item>
                <Building>1010345</Building>
                <!--Residence_tier01-->
                <Replacement>1555600003</Replacement>
                <!--AI_Residence_tier01-->
            </Item>
            <Item>
                <Building>1010346</Building>
                <!--Residence_tier01-->
                <Replacement>1555600004</Replacement>
                <!--AI_Residence_tier01-->
            </Item>
            <Item>
                <Building>1010347</Building>
                <!--Residence_tier01-->
                <Replacement>1555600005</Replacement>
                <!--AI_Residence_tier01-->
            </Item>
        </BuildingReplacements>
    </ModOp>

<!-- # Progression to Vanilla Engineers -->
    <ModOp GUID='1010346' Type="addNextSibling">
        <Asset>
            <!-- 
            Trigger to convert all jump engineers to vanilla engineers.
            Note: the trigger is re-registering itself.
            -->
            <Template>Trigger</Template>
            <Values>
            <Standard>
                <GUID>1555000016</GUID>
                <Name>Jump AI Building: Engineers</Name>
                <IconFilename>data/ui/2kimages/main/profiles/resident_tier04.png</IconFilename>
            </Standard>
            <Trigger>
                <TriggerCondition>
                <Template>ConditionPlayerCounter</Template>
                <Values>
                    <Condition />
                    <ConditionPlayerCounter>
                    <PlayerCounter>ObjectBuilt</PlayerCounter>
                    <Context>1555600004</Context>
                    <CounterAmount>1</CounterAmount>
                    </ConditionPlayerCounter>
                </Values>
                </TriggerCondition>
                <TriggerActions>
                <Item>
                    <TriggerAction>
                    <Template>ActionSetObjectGUID</Template>
                    <Values>
                        <Action />
                        <ActionSetObjectGUID>
                        <NewGUID>1010346</NewGUID>
                        </ActionSetObjectGUID>
                        <ObjectFilter>
                        <ObjectGUID>1555600004</ObjectGUID>
                        </ObjectFilter>
                    </Values>
                    </TriggerAction>
                </Item>
                <Item>
                    <TriggerAction>
                    <Template>ActionRegisterTrigger</Template>
                    <Values>
                        <Action />
                        <ActionRegisterTrigger>
                        <TriggerAsset>1555000016</TriggerAsset>
                        </ActionRegisterTrigger>
                    </Values>
                    </TriggerAction>
                </Item>
                </TriggerActions>
            </Trigger>
            <TriggerSetup>
                <UsedBySecondParties>1</UsedBySecondParties>
            </TriggerSetup>
            </Values>
        </Asset>
        </ModOp>

</ModOps>